monitor/__init__.py
monitor/admin.py
monitor/apps.py
monitor/models.py
monitor/tests.py
monitor/urls.py
monitor/views.py
monitor/migrations/0001_initial.py
monitor/migrations/__init__.py
realpython_django_monitor-1.1.0.dist-info/METADATA
realpython_django_monitor-1.1.0.dist-info/WHEEL
realpython_django_monitor-1.1.0.dist-info/top_level.txt
realpython_django_monitor-1.1.0.dist-info/RECORD
