Metadata-Version: 2.1
Name: realpython-django-monitor
Version: 1.1.0
Summary: Sample installable django app
Project-URL: repository, https://upload.pypi.org/legacy/
Classifier: Development Status :: 4 - Beta
Classifier: Environment :: Web Environment
Classifier: Intended Audience :: Developers
Classifier: Operating System :: OS Independent
Classifier: Programming Language :: Python :: 3 :: Only
Classifier: Programming Language :: Python :: 3.8
Classifier: Programming Language :: Python :: 3.9
Classifier: Programming Language :: Python :: 3.10
Classifier: Programming Language :: Python :: 3.11
Classifier: Programming Language :: Python :: 3.12
Classifier: Programming Language :: Python :: Implementation :: CPython
Classifier: Topic :: Software Development :: Libraries :: Application Frameworks
Classifier: Topic :: Software Development :: Libraries :: Python Modules
Requires-Python: >=3.8
Requires-Dist: Django>=4.2
Provides-Extra: dev
Requires-Dist: build==1.2.1; extra == "dev"
Requires-Dist: nox==2024.4.15; extra == "dev"
Requires-Dist: twine==5.1.1; extra == "dev"
